carbon/__init__.py
carbon/api_client.py
carbon/api_response.py
carbon/apis/__init__.py
carbon/apis/path_to_api.py
carbon/apis/paths/__init__.py
carbon/apis/paths/add_webhook.py
carbon/apis/paths/auth_v1_access_token.py
carbon/apis/paths/auth_v1_white_labeling.py
carbon/apis/paths/create_user_file_tags.py
carbon/apis/paths/data_sources.py
carbon/apis/paths/data_sources_tags_add.py
carbon/apis/paths/data_sources_tags_remove.py
carbon/apis/paths/delete_files.py
carbon/apis/paths/delete_files_v2.py
carbon/apis/paths/delete_user_file_tags.py
carbon/apis/paths/delete_users.py
carbon/apis/paths/delete_webhook_webhook_id.py
carbon/apis/paths/embeddings.py
carbon/apis/paths/fetch_urls.py
carbon/apis/paths/fetch_webpage.py
carbon/apis/paths/fetch_youtube_transcript.py
carbon/apis/paths/integrations_azure_blob_storage.py
carbon/apis/paths/integrations_azure_blob_storage_files.py
carbon/apis/paths/integrations_confluence_list.py
carbon/apis/paths/integrations_confluence_sync.py
carbon/apis/paths/integrations_connect.py
carbon/apis/paths/integrations_data_crm_accounts.py
carbon/apis/paths/integrations_data_crm_accounts_id.py
carbon/apis/paths/integrations_data_crm_contacts.py
carbon/apis/paths/integrations_data_crm_contacts_id.py
carbon/apis/paths/integrations_data_crm_leads.py
carbon/apis/paths/integrations_data_crm_leads_id.py
carbon/apis/paths/integrations_data_crm_opportunities.py
carbon/apis/paths/integrations_data_crm_opportunities_id.py
carbon/apis/paths/integrations_data_github_issues.py
carbon/apis/paths/integrations_data_github_issues_issue_number.py
carbon/apis/paths/integrations_data_github_pull_requests.py
carbon/apis/paths/integrations_data_github_pull_requests_comments.py
carbon/apis/paths/integrations_data_github_pull_requests_commits.py
carbon/apis/paths/integrations_data_github_pull_requests_files.py
carbon/apis/paths/integrations_data_github_pull_requests_pull_number.py
carbon/apis/paths/integrations_document360.py
carbon/apis/paths/integrations_files_sync.py
carbon_python_sdk-0.2.56.dist-info/LICENSE
carbon_python_sdk-0.2.56.dist-info/METADATA
carbon_python_sdk-0.2.56.dist-info/WHEEL
carbon_python_sdk-0.2.56.dist-info/RECORD
